xbstrap_version_bumper/__init__.py
xbstrap_version_bumper/__main__.py
xbstrap_version_bumper/linecounted_yaml.py
xbstrap_version_bumper/main.py
xbstrap_version_bumper-0.0.6.dist-info/LICENSE
xbstrap_version_bumper-0.0.6.dist-info/METADATA
xbstrap_version_bumper-0.0.6.dist-info/WHEEL
xbstrap_version_bumper-0.0.6.dist-info/entry_points.txt
xbstrap_version_bumper-0.0.6.dist-info/top_level.txt
xbstrap_version_bumper-0.0.6.dist-info/RECORD
