Metadata-Version: 2.1
Name: xbstrap_version_bumper
Version: 0.0.6
Summary: xbstrap distro auto version bumper
Author-email: Alexander Richards <electrodeyt@gmail.com>
Project-URL: Homepage, https://github.com/ElectrodeYT/xbstrap_version_bumper
Project-URL: Issues, https://github.com/ElectrodeYT/xbstrap_version_bumper/issues
Classifier: Programming Language :: Python :: 3
Classifier: License :: OSI Approved :: MIT License
Classifier: Operating System :: OS Independent
Requires-Python: >=3.8
License-File: LICENSE
Requires-Dist: GitPython >=3.1.43
Requires-Dist: requests >=2.31.0
Requires-Dist: ruamel.yaml >=0.18.6
Requires-Dist: libversion >=1.2.4
